{
  "id": "images",
  "childProcessIds": [],
  "name": "Images",
  "desc": "Any collection of image files",
  "executor": "INGEST",
  "documentationUrl": "",
  "code": {
    "repository": "NA",
    "uri": ""
  },
  "computeDefaults": [],
  "paramMapJson": "",
  "formJson": "",
  "webOptimizationJson": "s3://<RESOURCES_BUCKET>/<PROCESS_DIRECTORY>/process-output.json",
  "fileMappingRules": [
    {
      "description": "Images",
      "min": 1,
      "isSample": false,
      "fileNamePatterns": [
        { 
        "exampleName": "*", 
        "description": "Any Image", 
        "sampleMatchingPattern": "[\\S ]*"
        }
      ]
    }
  ]
}
